KS903_Ntural_Voice_bata_004/__init__.py
KS903NaturalIntonationAIVoice_Bate_vr_4-4.0.1.dist-info/METADATA
KS903NaturalIntonationAIVoice_Bate_vr_4-4.0.1.dist-info/WHEEL
KS903NaturalIntonationAIVoice_Bate_vr_4-4.0.1.dist-info/top_level.txt
KS903NaturalIntonationAIVoice_Bate_vr_4-4.0.1.dist-info/RECORD
