Metadata-Version: 2.1
Name: KS903NaturalIntonationAIVoice-Bate-vr-4
Version: 4.0.1
Summary: say's speech NaturalIntonation AI_Sample_Bates_Voice_Base_library for KS903:AI_Sample_Bates_Voice_Base__Versions_4.0.1__
Home-page: https://github.com/NPO_KS903_KATUYOSHI/say's_speech_NaturalIntonation_AI_Sample_Bates_Voice_Base_library_for_KS903:AI_Sample_Bates_Voice_Base__Versions_4.0.1__
Author: NPO_KS_903.lnc(President: Takeshi Kumura, Director: Takuma Ozawa)
Author-email: xksxkatuyoshi0009@gmail.com
License: MIT
Keywords: say's speech NaturalIntonation AI Sample Bates Voice_Base_library for KS903
Platform: UNKNOWN
Classifier: Development Status :: 3 - Alpha
Classifier: Intended Audience :: Developers
Classifier: License :: OSI Approved :: MIT License
Classifier: Programming Language :: Python :: 3
Classifier: Programming Language :: Python :: 3.8
Requires-Dist: pyttsx3
